grizz/__init__.py
grizz/ingestor/__init__.py
grizz/ingestor/base.py
grizz/ingestor/clickhouse.py
grizz/ingestor/csv.py
grizz/ingestor/parquet.py
grizz/ingestor/transform.py
grizz/ingestor/vanilla.py
grizz/testing/__init__.py
grizz/testing/fixture.py
grizz/transformer/__init__.py
grizz/transformer/base.py
grizz/transformer/casting.py
grizz/transformer/columns.py
grizz/transformer/concat.py
grizz/transformer/datetime.py
grizz/transformer/diff.py
grizz/transformer/duplicate.py
grizz/transformer/fill.py
grizz/transformer/function.py
grizz/transformer/json.py
grizz/transformer/null.py
grizz/transformer/replace.py
grizz/transformer/selection.py
grizz/transformer/sequential.py
grizz/transformer/sorting.py
grizz/transformer/sql.py
grizz/transformer/string.py
grizz/transformer/time.py
grizz/utils/__init__.py
grizz/utils/column.py
grizz/utils/datetime.py
grizz/utils/factory.py
grizz/utils/format.py
grizz/utils/imports.py
grizz/utils/interval.py
grizz/utils/noop.py
grizz/utils/path.py
grizz-0.1.1.dist-info/LICENSE
grizz-0.1.1.dist-info/METADATA
grizz-0.1.1.dist-info/WHEEL
grizz-0.1.1.dist-info/RECORD
