Metadata-Version: 2.1
Name: grizz
Version: 0.1.1
Summary: A light library to preprocess data with polars
Home-page: https://github.com/durandtibo/grizz
License: BSD-3-Clause
Keywords: polars,DataFrame,ingestor,transformer
Author: Thibaut Durand
Author-email: durand.tibo+gh@gmail.com
Requires-Python: >=3.9,<3.14
Classifier: Development Status :: 4 - Beta
Classifier: Intended Audience :: Developers
Classifier: Intended Audience :: Information Technology
Classifier: Intended Audience :: Science/Research
Classifier: License :: OSI Approved :: BSD License
Classifier: Operating System :: POSIX :: Linux
Classifier: Programming Language :: Python :: 3
Classifier: Programming Language :: Python :: 3.9
Classifier: Programming Language :: Python :: 3.10
Classifier: Programming Language :: Python :: 3.11
Classifier: Programming Language :: Python :: 3.12
Classifier: Programming Language :: Python :: 3.13
Classifier: Topic :: Scientific/Engineering
Classifier: Topic :: Software Development :: Libraries
Provides-Extra: all
Requires-Dist: clickhouse-connect (>=0.7,<1.0) ; extra == "all"
Requires-Dist: coola (>=0.8.5,<1.0)
Requires-Dist: iden (>=0.1,<1.0)
Requires-Dist: objectory (>=0.2,<1.0)
Requires-Dist: polars (>=1.0,<2.0)
Requires-Dist: pyarrow (>=10.0,<19.0) ; extra == "all"
Requires-Dist: tqdm (>=4.65,<5.0) ; extra == "all"
Project-URL: Repository, https://github.com/durandtibo/grizz
